<?xml version="1.0" encoding="utf-8"?>
<!DOCTYPE hibernate-mapping PUBLIC "-//Hibernate/Hibernate Mapping DTD 3.0//EN"
"http://hibernate.sourceforge.net/hibernate-mapping-3.0.dtd">
<!-- 
    Mapping file autogenerated by MyEclipse Persistence Tools
-->
<hibernate-mapping>
    <resultset name="vacciProgramResultSet">
    	<return-scalar column="RowNumber" type="integer"/>
    	<return-scalar column="Age" type="string"/>
    	<return-scalar column="HepB" type="string"/>
    	<return-scalar column="BCG" type="string"/>
    	<return-scalar column="OPV" type="string"/>
    	<return-scalar column="DPT" type="string"/>
    	<return-scalar column="DT" type="string"/>
    	<return-scalar column="MV" type="string"/>
    	<return-scalar column="MR" type="string"/>
    	<return-scalar column="MMR" type="string"/>
    	<return-scalar column="MM" type="string"/>
    	<return-scalar column="JE" type="string"/>
    	<return-scalar column="AECM" type="string"/>
    	<return-scalar column="ACECM" type="string"/>
    	<return-scalar column="AHA" type="string"/>
    	<return-scalar column="IHA" type="string"/>
    </resultset>
</hibernate-mapping>
